aioketraapi/__init__.py
aioketraapi/api_client.py
aioketraapi/configuration.py
aioketraapi/exceptions.py
aioketraapi/group.py
aioketraapi/keypad.py
aioketraapi/model_helper.py
aioketraapi/n4_hub.py
aioketraapi/oauth.py
aioketraapi/rest.py
aioketraapi/api/__init__.py
aioketraapi/api/group_operations_api.py
aioketraapi/api/hub_operations_api.py
aioketraapi/api/keypad_operations_api.py
aioketraapi/api/lamp_operations_api.py
aioketraapi/api/scene_operations_api.py
aioketraapi/models/__init__.py
aioketraapi/models/button.py
aioketraapi/models/button_change.py
aioketraapi/models/button_change_all_of.py
aioketraapi/models/button_change_notification.py
aioketraapi/models/group.py
aioketraapi/models/group_state_change.py
aioketraapi/models/group_state_change_all_of.py
aioketraapi/models/hub_ready.py
aioketraapi/models/hub_ready_all_of.py
aioketraapi/models/inline_response200.py
aioketraapi/models/inline_response2001.py
aioketraapi/models/inline_response20010.py
aioketraapi/models/inline_response20011.py
aioketraapi/models/inline_response20012.py
aioketraapi/models/inline_response20013.py
aioketraapi/models/inline_response20014.py
aioketraapi/models/inline_response2002.py
aioketraapi/models/inline_response2003.py
aioketraapi/models/inline_response2004.py
aioketraapi/models/inline_response2004_content.py
aioketraapi/models/inline_response2005.py
aioketraapi/models/inline_response2006.py
aioketraapi/models/inline_response2007.py
aioketraapi/models/inline_response2008.py
aioketraapi/models/inline_response2009.py
aioketraapi/models/inline_response200_content.py
aioketraapi/models/keypad.py
aioketraapi/models/lamp.py
aioketraapi/models/lamp_state.py
aioketraapi/models/lamp_state_all_of.py
aioketraapi/models/lamp_state_parameters.py
aioketraapi/models/level.py
aioketraapi/models/notifications.py
aioketraapi/models/publish_begin.py
aioketraapi/models/publish_begin_all_of.py
aioketraapi/models/scene.py
aioketraapi/models/websocket_v2_notification.py
aioketraapi-0.1.12.dist-info/METADATA
aioketraapi-0.1.12.dist-info/WHEEL
aioketraapi-0.1.12.dist-info/top_level.txt
aioketraapi-0.1.12.dist-info/RECORD
