Metadata-Version: 2.1
Name: aioketraapi
Version: 0.1.12
Summary: Ketra Lighting API
Home-page: https://github.com/s4v4g3/aio-ketra-api.git
Author: Joe Savage
Author-email: joe@savage.zone
Keywords: OpenAPI,OpenAPI-Generator,Ketra Lighting API
Requires-Python: >=3.6
Requires-Dist: urllib3 >=1.15
Requires-Dist: six >=1.10
Requires-Dist: certifi
Requires-Dist: python-dateutil
Requires-Dist: aiohttp >=3.0.0
